oneNeuron/__init__.py
oneNeuron/perceptron.py
utils/__init__.py
utils/all_utils.py
oneNeuron_pypi_abhishekvarma12345-0.1.0.dist-info/LICENSE
oneNeuron_pypi_abhishekvarma12345-0.1.0.dist-info/METADATA
oneNeuron_pypi_abhishekvarma12345-0.1.0.dist-info/WHEEL
oneNeuron_pypi_abhishekvarma12345-0.1.0.dist-info/top_level.txt
oneNeuron_pypi_abhishekvarma12345-0.1.0.dist-info/RECORD
