Metadata-Version: 2.1
Name: oneNeuron-pypi-abhishekvarma12345
Version: 0.1.0
Summary: Its an implementation of perceptron and can create plots for logic gates
Home-page: https://github.com/abhishekvarma12345/oneNeuron_pypi
Author: abhishekvarma12345
Author-email: abhishekvarmad@gmail.com
License: UNKNOWN
Project-URL: Bug Tracker, https://github.com/abhishekvarma12345/oneNeuron_pypi/issues
Platform: UNKNOWN
Classifier: Programming Language :: Python :: 3
Classifier: License :: OSI Approved :: MIT License
Classifier: Operating System :: OS Independent
Requires-Python: >=3.7
License-File: LICENSE
Requires-Dist: numpy
Requires-Dist: tqdm
Requires-Dist: matplotlib
Requires-Dist: joblib
